results/__init__.py
results/command.py
results/constants.py
results/createdrop.py
results/database.py
results/formatting.py
results/inserting.py
results/loading.py
results/notify.py
results/paging.py
results/psyco.py
results/rows.py
results/schemas.py
results/statements.py
results/syntax.py
results/tempdb.py
results/typeguess.py
results/urls.py
results/dbdiff/__init__.py
results/dbdiff/changes.py
results/dbdiff/migra.py
results/dbdiff/statements.py
results/dbdiff/util.py
results/schemainspect/__init__.py
results/schemainspect/get.py
results/schemainspect/inspected.py
results/schemainspect/inspector.py
results/schemainspect/misc.py
results/schemainspect/tableformat.py
results/schemainspect/pg/__init__.py
results/schemainspect/pg/obj.py
results/schemainspect/pg/sql/collations.sql
results/schemainspect/pg/sql/constraints.sql
results/schemainspect/pg/sql/deps.sql
results/schemainspect/pg/sql/domains.sql
results/schemainspect/pg/sql/enums.sql
results/schemainspect/pg/sql/extensions.sql
results/schemainspect/pg/sql/extoids.sql
results/schemainspect/pg/sql/functions.sql
results/schemainspect/pg/sql/indexes.sql
results/schemainspect/pg/sql/privileges.sql
results/schemainspect/pg/sql/relations.sql
results/schemainspect/pg/sql/rlspolicies.sql
results/schemainspect/pg/sql/schemas.sql
results/schemainspect/pg/sql/sequences.sql
results/schemainspect/pg/sql/triggers.sql
results/schemainspect/pg/sql/types.sql
results/utils/__init__.py
results/utils/sqla.py
results-1.4.1767098839.dist-info/licenses/LICENSE.txt
results-1.4.1767098839.dist-info/METADATA
results-1.4.1767098839.dist-info/WHEEL
results-1.4.1767098839.dist-info/entry_points.txt
results-1.4.1767098839.dist-info/top_level.txt
results-1.4.1767098839.dist-info/RECORD
