Metadata-Version: 2.4
Name: results
Version: 1.4.1767098839
License-File: LICENSE.txt
Requires-Dist: psycopg[pool]
Requires-Dist: click
Dynamic: license-file
